pixie16/C_library_sdk.py
pixie16/__init__.py
pixie16/_version.py
pixie16/analyze.py
pixie16/config.py
pixie16/control.py
pixie16/create_variable_list.py
pixie16/pipeline.py
pixie16/plot.py
pixie16/py.typed
pixie16/scan.py
pixie16/tasks.py
pixie16/variables.py
pixie16/cli/__init__.py
pixie16/cli/binary_browser.py
pixie16/cli/coincidence.py
pixie16/cli/parameter_scan.py
pixie16/data/default.json
pixie16/read/__init__.py
pixie16/read/mca.py
pixie16/read/list_mode/__init__.py
pixie16/read/list_mode/list_mode_data_reader.py
pixie16/read/settings/__init__.py
pixie16/read/settings/compare.py
pixie16/read/settings/convert_settings.py
pixie16/read/settings/field_classes.py
pixie16/read/settings/file_format.py
pixie16/read/settings/old_settings_class.py
pixie16/read/settings/settings_class.py
pixie16/read/settings/units.py
pixie16/ui/__init__.py
pixie16/ui/helper.py
pixie16/ui/plot.py
pixie16/ui/widgets.py
pixie16/ui/binary_browser/__init__.py
pixie16/ui/binary_browser/app.py
pixie16/ui/binary_browser/channel_select.py
pixie16/ui/binary_browser/data_model.py
pixie16/ui/binary_browser/fast_trigger.py
pixie16/ui/coincidence/__init__.py
pixie16/ui/coincidence/app.py
pixie16/ui/coincidence/coincidence_plots.py
pixie16/ui/coincidence/main_widget.py
pypixie16-3.0.0.dist-info/LICENSE.txt
pypixie16-3.0.0.dist-info/METADATA
pypixie16-3.0.0.dist-info/WHEEL
pypixie16-3.0.0.dist-info/entry_points.txt
pypixie16-3.0.0.dist-info/top_level.txt
pypixie16-3.0.0.dist-info/RECORD
