Metadata-Version: 2.1
Name: pypixie16
Version: 3.0.0
Author-email: Arun Persaud <apersaud@lbl.gov>, Ariel Amsellem <ajamsellem@lbl.gov>, Andrew Rosenstrom <arosenstrom@lbl.gov>, Brian Mak <brianmak@lbl.gov>, Mauricio Ayllon Unzueta <mayllonu@lbl.gov>, Will Larsen <wlarsen@lbl.gov>, Caroline Egan <cegan@lbl.gov>
License: Pixie16 Python Interface (Pixie 16) v1 Copyright (c) 2019, The Regents
Project-URL: documentation, https://pypixie16.readthedocs.io/en/latest/
Project-URL: homepage, https://bitbucket.org/berkeleylab/pypixie16
Project-URL: issues, https://bitbucket.org/berkeleylab/pypixie16/issues
Project-URL: changelog, https://bitbucket.org/berkeleylab/pypixie16/src/main/CHANGELOG.md
Classifier: Programming Language :: Python :: 3
Classifier: Development Status :: 5 - Production/Stable
Classifier: License :: OSI Approved :: BSD License
Classifier: Intended Audience :: Science/Research
Classifier: Programming Language :: Python :: 3.9
Classifier: Programming Language :: Python :: 3.10
Classifier: Programming Language :: Python :: 3.11
Classifier: Programming Language :: Python :: 3.12
Classifier: Topic :: Scientific/Engineering :: Physics
Requires-Python: >=3.9
License-File: LICENSE.txt
Requires-Dist: appdirs
Requires-Dist: bitstruct
Requires-Dist: docopt
Requires-Dist: fast-histogram
Requires-Dist: matplotlib
Requires-Dist: msgspec
Requires-Dist: more-itertools
Requires-Dist: numpy
Requires-Dist: pandas
Requires-Dist: pint
Requires-Dist: platformdirs
Requires-Dist: PyQt6
Requires-Dist: rich
Requires-Dist: setuptools
Requires-Dist: setuptools-scm
Requires-Dist: tables
Provides-Extra: docs
Requires-Dist: alabaster ; extra == 'docs'
Requires-Dist: markupsafe ; extra == 'docs'
Requires-Dist: sphinx ; extra == 'docs'
Requires-Dist: sphinxcontrib-napoleon ; extra == 'docs'
Requires-Dist: recommonmark ; extra == 'docs'
Provides-Extra: fast
Requires-Dist: cbitstruct ; extra == 'fast'
Provides-Extra: test
Requires-Dist: pytest ; extra == 'test'
Requires-Dist: pytest-cov ; extra == 'test'
